threedi_cmd/__init__.py
threedi_cmd/console.py
threedi_cmd/errors.py
threedi_cmd/example.py
threedi_cmd/jinja2_time.py
threedi_cmd/logger.py
threedi_cmd/parser.py
threedi_cmd/test.py
threedi_cmd/version.py
threedi_cmd/commands/__init__.py
threedi_cmd/commands/active_simulations.py
threedi_cmd/commands/api.py
threedi_cmd/commands/app_definitions.py
threedi_cmd/commands/callbacks.py
threedi_cmd/commands/main.py
threedi_cmd/commands/models.py
threedi_cmd/commands/scenarios.py
threedi_cmd/commands/settings.py
threedi_cmd/commands/slack_notify.py
threedi_cmd/commands/suite.py
threedi_cmd/commands/utils.py
threedi_cmd/models/__init__.py
threedi_cmd/models/actions.py
threedi_cmd/models/base.py
threedi_cmd/models/boundary_conditions.py
threedi_cmd/models/breach.py
threedi_cmd/models/errors.py
threedi_cmd/models/initial_waterlevels.py
threedi_cmd/models/lateral.py
threedi_cmd/models/leakage.py
threedi_cmd/models/monitor.py
threedi_cmd/models/postprocessing.py
threedi_cmd/models/rain.py
threedi_cmd/models/rasteredit.py
threedi_cmd/models/revision.py
threedi_cmd/models/savedstate.py
threedi_cmd/models/scenario.py
threedi_cmd/models/settings.py
threedi_cmd/models/simulation.py
threedi_cmd/models/sources_sinks.py
threedi_cmd/models/structure_control.py
threedi_cmd/models/substance.py
threedi_cmd/models/waitfor.py
threedi_cmd/models/wind.py
threedi_cmd/plugins/__init__.py
threedi_cmd/plugins/models.py
threedi_cmd/plugins/tools.py
threedi_cmd/schematisation_uploader/__init__.py
threedi_cmd/schematisation_uploader/db.py
threedi_cmd/schematisation_uploader/example.py
threedi_cmd/schematisation_uploader/main.py
threedi_cmd/schematisation_uploader/yaml_converter.py
threedi_cmd/websockets/__init__.py
threedi_cmd/websockets/clients.py
threedi_cmd/websockets/settings.py
threedi_cmd-0.3.11.dist-info/licenses/AUTHORS.rst
threedi_cmd-0.3.11.dist-info/licenses/LICENSE
threedi_cmd-0.3.11.dist-info/METADATA
threedi_cmd-0.3.11.dist-info/WHEEL
threedi_cmd-0.3.11.dist-info/entry_points.txt
threedi_cmd-0.3.11.dist-info/top_level.txt
threedi_cmd-0.3.11.dist-info/RECORD
