Metadata-Version: 2.4
Name: threedi-cmd
Version: 0.3.11
Summary: Python 3Di command line client
Author-email: Jelle Prins <jelle.prins@nelen-schuurmans.nl>
Maintainer-email: Jelle Prins <jelle.prins@nelen-schuurmans.nl>, Daan van Ingen <daan.vaningen@nelen-schuurmans.nl>
License: MIT License
Project-URL: Repository, https://github.com/nens/threedi-cmd
Keywords: 3Di, client, command line, scenario
Classifier: Intended Audience :: Developers
Classifier: License :: OSI Approved :: BSD License
Classifier: Natural Language :: English
Classifier: Programming Language :: Python :: 3
Classifier: Topic :: Scientific/Engineering
Requires-Python: >=3.10
License-File: LICENSE
License-File: AUTHORS.rst
Requires-Dist: threedi-api-client
Requires-Dist: PyYAML>=5.1
Requires-Dist: websockets>=14.1
Requires-Dist: arrow>=0.14.4
Requires-Dist: Jinja2>=2.10.1
Requires-Dist: jinja2-time>=0.2.0
Requires-Dist: slackclient>=2.8.2
Requires-Dist: click>=7.1.2
Requires-Dist: requests>=2.25.0
Requires-Dist: rich>=9.4.0
Requires-Dist: typer>=0.3.2
Requires-Dist: threedi-schema>=0.300.26
Provides-Extra: test
Requires-Dist: pytest; extra == "test"
Dynamic: license-file
